pulumi_fastly/__init__.py
pulumi_fastly/_inputs.py
pulumi_fastly/_utilities.py
pulumi_fastly/alert.py
pulumi_fastly/compute_acl.py
pulumi_fastly/compute_acl_entries.py
pulumi_fastly/configstore.py
pulumi_fastly/configstore_entries.py
pulumi_fastly/custom_dashboard.py
pulumi_fastly/domain_v1.py
pulumi_fastly/domain_v1_service_link.py
pulumi_fastly/get_compute_acls.py
pulumi_fastly/get_configstores.py
pulumi_fastly/get_datacenters.py
pulumi_fastly/get_dictionaries.py
pulumi_fastly/get_domains_v1.py
pulumi_fastly/get_fastly_ip_ranges.py
pulumi_fastly/get_kvstores.py
pulumi_fastly/get_ngwaf_account_lists.py
pulumi_fastly/get_ngwaf_account_rules.py
pulumi_fastly/get_ngwaf_account_signals.py
pulumi_fastly/get_ngwaf_alert_datadog_integration.py
pulumi_fastly/get_ngwaf_alert_jira_integration.py
pulumi_fastly/get_ngwaf_alert_mailing_list_integration.py
pulumi_fastly/get_ngwaf_alert_microsoft_teams_integration.py
pulumi_fastly/get_ngwaf_alert_opsgenie_integration.py
pulumi_fastly/get_ngwaf_alert_pagerduty_integration.py
pulumi_fastly/get_ngwaf_alert_slack_integration.py
pulumi_fastly/get_ngwaf_alert_webhook_integration.py
pulumi_fastly/get_ngwaf_redactions.py
pulumi_fastly/get_ngwaf_thresholds.py
pulumi_fastly/get_ngwaf_virtual_patches.py
pulumi_fastly/get_ngwaf_workspace_lists.py
pulumi_fastly/get_ngwaf_workspace_rules.py
pulumi_fastly/get_ngwaf_workspace_signals.py
pulumi_fastly/get_ngwaf_workspaces.py
pulumi_fastly/get_package_hash.py
pulumi_fastly/get_secretstores.py
pulumi_fastly/get_services.py
pulumi_fastly/get_tls_activation.py
pulumi_fastly/get_tls_activation_ids.py
pulumi_fastly/get_tls_certificate.py
pulumi_fastly/get_tls_certificate_ids.py
pulumi_fastly/get_tls_configuration.py
pulumi_fastly/get_tls_configuration_ids.py
pulumi_fastly/get_tls_domain.py
pulumi_fastly/get_tls_platform_certificate.py
pulumi_fastly/get_tls_platform_certificate_ids.py
pulumi_fastly/get_tls_private_key.py
pulumi_fastly/get_tls_private_key_ids.py
pulumi_fastly/get_tls_subscription.py
pulumi_fastly-11.1.0.dist-info/METADATA
pulumi_fastly-11.1.0.dist-info/WHEEL
pulumi_fastly-11.1.0.dist-info/top_level.txt
pulumi_fastly-11.1.0.dist-info/RECORD
